h5glance/__init__.py
h5glance/__main__.py
h5glance/completer.py
h5glance/completion.bash
h5glance/completion.zsh
h5glance/copypath.js
h5glance/datatypes.py
h5glance/html.py
h5glance/html_cli.py
h5glance/ipython.py
h5glance/terminal.py
h5glance/treeview.css
h5glance/utils.py
h5glance-0.9.0.dist-info/entry_points.txt
h5glance-0.9.0.dist-info/LICENSE
h5glance-0.9.0.dist-info/WHEEL
h5glance-0.9.0.dist-info/METADATA
h5glance-0.9.0.dist-info/RECORD
