Metadata-Version: 2.3
Name: h5glance
Version: 0.9.0
Summary: Explore HDF5 files in an HTML view
Author-email: European XFEL GmbH <da-support@xfel.eu>
Maintainer: Thomas Kluyver
Requires-Python: >=3.9
Classifier: License :: OSI Approved :: BSD License
Requires-Dist: h5py >=2.10
Requires-Dist: htmlgen
Project-URL: Changelog, https://github.com/European-XFEL/h5glance/blob/master/CHANGES.rst
Project-URL: Source, https://github.com/European-XFEL/h5glance
